apistar_cors_hooks.py
apistar_cors_hooks-0.1.1.dist-info/LICENSE.txt
apistar_cors_hooks-0.1.1.dist-info/METADATA
apistar_cors_hooks-0.1.1.dist-info/RECORD
apistar_cors_hooks-0.1.1.dist-info/WHEEL
apistar_cors_hooks-0.1.1.dist-info/top_level.txt
